vaxadium/__init__.py
vaxadium/_version.py
vaxadium/axes.py
vaxadium/cli_density.py
vaxadium/cli_dls.py
vaxadium/cli_macros.py
vaxadium/cli_vaxadium.py
vaxadium/configuration.py
vaxadium/constants.py
vaxadium/data_descriptors.py
vaxadium/defaults.py
vaxadium/experiment.py
vaxadium/logging_setup.py
vaxadium/physics.py
vaxadium/processors.py
vaxadium/runner.py
vaxadium/scaler.py
vaxadium/checks/__init__.py
vaxadium/checks/basechecker.py
vaxadium/checks/calibration.py
vaxadium/checks/convergence.py
vaxadium/checks/data.py
vaxadium/checks/extractor.py
vaxadium/checks/sample.py
vaxadium/core/axis_generators.py
vaxadium/core/detector.py
vaxadium/core/form_factors.py
vaxadium/core/fourier.py
vaxadium/core/units.py
vaxadium/g4diffsim/fitting.py
vaxadium/g4diffsim/macro_maker.py
vaxadium/g4diffsim/macros.py
vaxadium/g4diffsim/simulation.py
vaxadium/io/__init__.py
vaxadium/io/nexus_reader.py
vaxadium/io/outputs.py
vaxadium/io/serializer_factory.py
vaxadium/io/serializers.py
vaxadium/io/utils.py
vaxadium/transmission/__init__.py
vaxadium/transmission/attenuator.py
vaxadium/transmission/beam.py
vaxadium/transmission/cylinder_yz.py
vaxadium/transmission/cylinder_yz_runner.py
vaxadium/transmission/direction.py
vaxadium/transmission/illuminated_yz.py
vaxadium/transmission/illuminated_yz_runner.py
vaxadium/transmission/scatterer.py
vaxadium/transmission/transmission_map.py
vaxadium/transmission/yz_generator.py
vaxadium-0.3.1.dist-info/METADATA
vaxadium-0.3.1.dist-info/WHEEL
vaxadium-0.3.1.dist-info/entry_points.txt
vaxadium-0.3.1.dist-info/licenses/AUTHORS.rst
vaxadium-0.3.1.dist-info/licenses/LICENSE
vaxadium-0.3.1.dist-info/RECORD
