Metadata-Version: 2.1
Name: vaxadium
Version: 0.3.1
Summary: Processes total scattering data using Monte Carlo simulations
Project-URL: Homepage, https://github.com/DiamondLightSource/vaxadium
Project-URL: Issues, https://github.com/DiamondLightSource/vaxadium/issues
Author-email: Dean Keeble <dean.keeble@diamond.ac.uk>
License-Expression: MIT
License-File: AUTHORS.rst
License-File: LICENSE
Keywords: vaxadium
Classifier: Programming Language :: Python :: 3.9
Classifier: Programming Language :: Python :: 3.10
Requires-Python: <3.11,>3.8
Requires-Dist: numpy
Requires-Dist: pint
Requires-Dist: pyfai
Requires-Dist: scikit-learn
Requires-Dist: scipy
Requires-Dist: swmr-tools
Requires-Dist: xraylib
